_portaudio.cpython-36m-darwin.so
pyaudio.py
PyAudioGithub-0.2.11.dist-info/METADATA
PyAudioGithub-0.2.11.dist-info/WHEEL
PyAudioGithub-0.2.11.dist-info/top_level.txt
PyAudioGithub-0.2.11.dist-info/RECORD
