Metadata-Version: 2.1
Name: PyAudioGithub
Version: 0.2.11
Summary: PortAudio Python Bindings
Home-page: http://people.csail.mit.edu/hubert/pyaudio/
Author: Hubert Pham
Author-email: UNKNOWN
License: UNKNOWN
Platform: UNKNOWN
